hanzoai/README.md
hanzoai/__init__.py
hanzoai/_base_client.py
hanzoai/_client.py
hanzoai/_compat.py
hanzoai/_constants.py
hanzoai/_exceptions.py
hanzoai/_files.py
hanzoai/_models.py
hanzoai/_qs.py
hanzoai/_resource.py
hanzoai/_response.py
hanzoai/_streaming.py
hanzoai/_types.py
hanzoai/_version.py
hanzoai/agents.py
hanzoai/auth.py
hanzoai/cluster.py
hanzoai/llm_client.py
hanzoai/mcp.py
hanzoai/py.typed
hanzoai/_utils/__init__.py
hanzoai/_utils/_logs.py
hanzoai/_utils/_proxy.py
hanzoai/_utils/_reflection.py
hanzoai/_utils/_streams.py
hanzoai/_utils/_sync.py
hanzoai/_utils/_transform.py
hanzoai/_utils/_typing.py
hanzoai/_utils/_utils.py
hanzoai/grpo/__init__.py
hanzoai/grpo/api_model_adapter.py
hanzoai/grpo/enhanced_api_model_adapter.py
hanzoai/grpo/enhanced_semantic_extractor.py
hanzoai/grpo/experience_manager.py
hanzoai/grpo/semantic_extractor.py
hanzoai/lib/.keep
hanzoai/resources/__init__.py
hanzoai/resources/access.py
hanzoai/resources/active.py
hanzoai/resources/add.py
hanzoai/resources/affiliates.py
hanzoai/resources/agents.py
hanzoai/resources/anthropic.py
hanzoai/resources/assemblyai.py
hanzoai/resources/assistants.py
hanzoai/resources/audit.py
hanzoai/resources/azure.py
hanzoai/resources/bedrock.py
hanzoai/resources/budget.py
hanzoai/resources/build.py
hanzoai/resources/campaigns.py
hanzoai/resources/cart.py
hanzoai/resources/chain.py
hanzoai/resources/checkout.py
hanzoai/resources/cohere.py
hanzoai/resources/completions.py
hanzoai/resources/containers.py
hanzoai/resources/coupons.py
hanzoai/resources/credentials.py
hanzoai/resources/customer.py
hanzoai/resources/db.py
hanzoai/resources/delete.py
hanzoai/resources/deployments.py
hanzoai/resources/device.py
hanzoai/resources/dns.py
hanzoai/resources/edge.py
hanzoai/resources/embeddings.py
hanzoai/resources/eu_assemblyai.py
hanzoai/resources/gateway.py
hanzoai/resources/gemini.py
hanzoai/resources/graphs.py
hanzoai/resources/guardrails.py
hanzoai/resources/health.py
hanzoai/resources/identity.py
hanzoai-2.1.2.dist-info/METADATA
hanzoai-2.1.2.dist-info/WHEEL
hanzoai-2.1.2.dist-info/licenses/LICENSE
hanzoai-2.1.2.dist-info/RECORD
