Metadata-Version: 2.3
Name: hanzoai
Version: 2.1.2
Summary: The official Python library for the Hanzo API
Project-URL: Homepage, https://github.com/hanzoai/python-sdk
Project-URL: Repository, https://github.com/hanzoai/python-sdk
Author-email: Hanzo <dev@hanzo.ai>
License: BSD-3-Clause
Classifier: Intended Audience :: Developers
Classifier: License :: OSI Approved :: BSD License
Classifier: Operating System :: MacOS
Classifier: Operating System :: Microsoft :: Windows
Classifier: Operating System :: OS Independent
Classifier: Operating System :: POSIX
Classifier: Operating System :: POSIX :: Linux
Classifier: Programming Language :: Python :: 3.9
Classifier: Programming Language :: Python :: 3.10
Classifier: Programming Language :: Python :: 3.11
Classifier: Programming Language :: Python :: 3.12
Classifier: Programming Language :: Python :: 3.13
Classifier: Topic :: Software Development :: Libraries :: Python Modules
Classifier: Typing :: Typed
Requires-Python: >=3.9
Requires-Dist: anyio<5,>=3.5.0
Requires-Dist: distro<2,>=1.7.0
Requires-Dist: h11>=0.16.0
Requires-Dist: httpx<1,>=0.23.0
Requires-Dist: pydantic<3,>=1.9.0
Requires-Dist: sniffio
Requires-Dist: typing-extensions<5,>=4.10
Requires-Dist: urllib3>=2.6.0
Provides-Extra: litellm
Requires-Dist: litellm>=1.0.0; extra == 'litellm'
